{"sections":{"main":{"type":"main-page","settings":{"show_title":false,"page_width":"medium"}},"d22879bb-7ce9-4290-9f54-2df07f90feff":{"type":"design_pack_-_video_with_text","disabled":true,"blocks":{"template--16667336638732__d22879bb-7ce9-4290-9f54-2df07f90feff-167395866646f6f7a8-0":{"type":"inset_image","disabled":true,"settings":{"inset_image_size":10,"image_alignment":"default"}},"template--16667336638732__d22879bb-7ce9-4290-9f54-2df07f90feff-167395866646f6f7a8-1":{"type":"small_text","disabled":true,"settings":{"small_text":"<p>Skin<\/p>"}},"template--16667336638732__d22879bb-7ce9-4290-9f54-2df07f90feff-167395866646f6f7a8-2":{"type":"heading","settings":{"title":"Style Skin","block_heading_color":"","block_heading_size":"","heading_level":"h2"}},"template--16667336638732__d22879bb-7ce9-4290-9f54-2df07f90feff-167395866646f6f7a8-3":{"type":"text","settings":{"text":"<p>Schenke deinem Device mit unseren Style Skins einen individuellen Look, der sich wie eine zweite Haut um dein Smartphone schmiegt.<br\/>Gleichzeitig schützt der Skin dein Smartphone zuverlässig vor Kratzern und weiteren Schäden.<\/p><p>Ganz egal ob du es bunt oder schlicht, modern oder klassisch oder einfach nur crazy möchtest – wir bieten dir eine riesige Auswahl unterschiedlichster Designs.<\/p>"}}},"block_order":["template--16667336638732__d22879bb-7ce9-4290-9f54-2df07f90feff-167395866646f6f7a8-0","template--16667336638732__d22879bb-7ce9-4290-9f54-2df07f90feff-167395866646f6f7a8-1","template--16667336638732__d22879bb-7ce9-4290-9f54-2df07f90feff-167395866646f6f7a8-2","template--16667336638732__d22879bb-7ce9-4290-9f54-2df07f90feff-167395866646f6f7a8-3"],"custom_css":["section {max-width: 1250px; margin: auto; margin-top: 50px; margin-bottom: 50px;}"],"settings":{"video":"shopify:\/\/files\/videos\/Untitled_0fec8143-4700-4354-8eff-396b0acbaf5d.mp4","autoplay":true,"loop":true,"show_controls":false,"image_position":"right","image_crop":"1:1","aspect_ratio":"3:2","mobile_aspect_ratio":"","text_alignment":"left","text_size":90,"text_width":50,"text_color":"#283144","text_background_color":"linear-gradient(0deg, rgba(255, 255, 255, 1), rgba(255, 255, 255, 1) 100%)","background_color":"","show_background_image":false,"animation":"none","base_width":100,"max_width":"","inner_padding":0,"outer_margin":35,"custom_css":".dsgn-pck__small-text p{\n  letter-spacing: 1px;\n  font-weight: 500;\n}\n\n.dsgn-pck__video video {\n  border-radius: 10px;\n}","mobile_custom_css":".dsgn-pck__video video {\n  border-radius: 0px;\n}","override_theme_font":false,"heading_font":"serif","main_font":"sans-serif"}},"1654028285738d53d0":{"type":"video","custom_css":["section {max-width: 1200px; margin: auto; margin-bottom: 50px;}"],"settings":{"subheading":"","title":"","video_url":"https:\/\/www.youtube.com\/watch?v=izczqzaOjTI","image":"shopify:\/\/shop_images\/Bildschirm_foto_2023-05-14_um_21.35.04.png","background_type":"boxed","video_size":"medium","autoplay":false,"background":"rgba(0,0,0,0)","text_color":"rgba(0,0,0,0)","custom_css":"","mobile_custom_css":"","override_theme_font":false}},"16540287657eccca14":{"type":"contact-form","settings":{"title":"Kontaktiere uns wenn du Fragen hast","content":"","text_1_heading":"","text_1_text":"","text_2_heading":"","text_2_text":"","background":"#fafafa","text_color":"rgba(0,0,0,0)","button_background":"rgba(0,0,0,0)","button_text_color":"rgba(0,0,0,0)","custom_css":"","mobile_custom_css":"","override_theme_font":false}}},"order":["main","d22879bb-7ce9-4290-9f54-2df07f90feff","1654028285738d53d0","16540287657eccca14"]}